glayout/__init__.py
glayout/pdk/__init__.py
glayout/pdk/mappedpdk.py
glayout/pdk/gf180_mapped/__init__.py
glayout/pdk/gf180_mapped/gf180_mapped.py
glayout/pdk/gf180_mapped/gf180mcu.drc
glayout/pdk/gf180_mapped/gf180mcu_drc.lydrc
glayout/pdk/gf180_mapped/gf180mcu_osu_sc_9T.spice
glayout/pdk/gf180_mapped/grules.py
glayout/pdk/sky130_mapped/__init__.py
glayout/pdk/sky130_mapped/grules.py
glayout/pdk/sky130_mapped/sky130.lydrc
glayout/pdk/sky130_mapped/sky130_add_npc.py
glayout/pdk/sky130_mapped/sky130_fd_sc_hd.spice
glayout/pdk/sky130_mapped/sky130_mapped.py
glayout/placement/__init__.py
glayout/placement/common_centroid_ab_ba.py
glayout/placement/four_transistor_interdigitized.py
glayout/placement/two_transistor_interdigitized.py
glayout/placement/two_transistor_place.py
glayout/primitives/__init__.py
glayout/primitives/fet.py
glayout/primitives/guardring.py
glayout/primitives/mimcap.py
glayout/primitives/resistor.py
glayout/primitives/via_gen.py
glayout/routing/L_route.py
glayout/routing/__init__.py
glayout/routing/c_route.py
glayout/routing/smart_route.py
glayout/routing/straight_route.py
glayout/spice/__init__.py
glayout/spice/netlist.py
glayout/util/__init__.py
glayout/util/comp_utils.py
glayout/util/component_array_create.py
glayout/util/geometry.py
glayout/util/port_utils.py
glayout/util/print_rules.py
glayout/util/routing.py
glayout/util/snap_to_grid.py
glayout-0.1.1.dist-info/licenses/LICENSE
glayout-0.1.1.dist-info/METADATA
glayout-0.1.1.dist-info/WHEEL
glayout-0.1.1.dist-info/top_level.txt
glayout-0.1.1.dist-info/RECORD
