Metadata-Version: 2.4
Name: glayout
Version: 0.1.1
Summary: A PDK-agnostic layout automation framework for analog circuit design
Author: OpenFASOC Team
Author-email: mehdi@umich.edu
Classifier: Development Status :: 4 - Beta
Classifier: Intended Audience :: Science/Research
Classifier: Topic :: Scientific/Engineering :: Electronic Design Automation (EDA)
Classifier: License :: OSI Approved :: MIT License
Classifier: Programming Language :: Python :: 3.10
Requires-Python: >=3.10
License-File: LICENSE
Requires-Dist: gdsfactory<=7.7.0,>6.0.0
Requires-Dist: numpy<=1.24.0,>1.21.0
Requires-Dist: pandas<=2.3.0,>1.3.0
Requires-Dist: matplotlib<=3.10.0,>3.4.0
Requires-Dist: klayout>=0.28.0
Requires-Dist: prettyprint
Requires-Dist: prettyprinttree
Requires-Dist: gdstk
Requires-Dist: svgutils
Requires-Dist: nltk
Requires-Dist: ipywidgets
Provides-Extra: dev
Requires-Dist: pytest>=7.0.0; extra == "dev"
Requires-Dist: pytest-cov>=3.0.0; extra == "dev"
Requires-Dist: black>=22.0.0; extra == "dev"
Requires-Dist: isort>=5.0.0; extra == "dev"
Requires-Dist: flake8>=4.0.0; extra == "dev"
Provides-Extra: ml
Requires-Dist: torch>=1.10.0; extra == "ml"
Requires-Dist: transformers>=4.0.0; extra == "ml"
Requires-Dist: scikit-learn>=1.0.0; extra == "ml"
Dynamic: author
Dynamic: author-email
Dynamic: classifier
Dynamic: description
Dynamic: description-content-type
Dynamic: license-file
Dynamic: provides-extra
Dynamic: requires-dist
Dynamic: requires-python
Dynamic: summary
